{
  "inputs": [
    [
      "low-period",
      200000
    ],
    [
      "high-extra-refills",
      4
    ],
    [
      "high-budget",
      60
    ],
    [
      "timer-both",
      true
    ]
  ],
  "series": {
    "irq-bounded[Baseline]": [
      {
        "stddev": 6.6583281184793925,
        "x": null,
        "y": 38397623.666666664
      }
    ],
    "irq-bounded[Interrupt]": [
      {
        "stddev": 4033.4221615562797,
        "x": 12,
        "y": 38227206.666666664
      },
      {
        "stddev": 3153.5555066200013,
        "x": 24,
        "y": 38243241.333333336
      },
      {
        "stddev": 3400.6934586933885,
        "x": 48,
        "y": 38314905
      },
      {
        "stddev": 509.2965737171221,
        "x": 96,
        "y": 38363906
      }
    ],
    "sporadic[Baseline]": [
      {
        "stddev": 12.662279942148386,
        "x": null,
        "y": 38398033.333333336
      }
    ],
    "sporadic[Interrupt]": [
      {
        "stddev": 4637.847453291236,
        "x": 12,
        "y": 36578366
      },
      {
        "stddev": 10786.934890567076,
        "x": 24,
        "y": 36752182.333333336
      },
      {
        "stddev": 747.2998059681269,
        "x": 48,
        "y": 37470599
      },
      {
        "stddev": 1106.088754726913,
        "x": 96,
        "y": 37940240.666666664
      }
    ]
  }
}