{
  "inputs": [
    [
      "high-extra-refills",
      4
    ],
    [
      "high-budget",
      120
    ],
    [
      "low-period",
      12500
    ],
    [
      "timer-both",
      true
    ]
  ],
  "series": {
    "correct-charge/[Interrupt]": [
      {
        "stddev": 12580.623606695071,
        "x": 83333.33333333333,
        "y": 30411134.666666668
      },
      {
        "stddev": 59.21430007467228,
        "x": 41666.666666666664,
        "y": 31900586.666666668
      },
      {
        "stddev": 3056.0503922546827,
        "x": 20833.333333333332,
        "y": 31569467
      },
      {
        "stddev": 410.8904963612568,
        "x": 10416.666666666666,
        "y": 31774585
      }
    ],
    "irq-bounded/[Interrupt]": [
      {
        "stddev": 79663.58879898227,
        "x": 83333.33333333333,
        "y": 31715410.333333332
      },
      {
        "stddev": 967.6399123640983,
        "x": 41666.666666666664,
        "y": 31912104
      },
      {
        "stddev": 371.45973312505,
        "x": 20833.333333333332,
        "y": 31914305.333333332
      },
      {
        "stddev": 92.55448845590004,
        "x": 10416.666666666666,
        "y": 31949194.666666668
      }
    ],
    "sporadic/[Interrupt]": [
      {
        "stddev": 4364.321405823972,
        "x": 83333.33333333333,
        "y": 28784788.666666668
      },
      {
        "stddev": 2575.655709393888,
        "x": 41666.666666666664,
        "y": 31134432.333333332
      },
      {
        "stddev": 1833.8708605933334,
        "x": 20833.333333333332,
        "y": 31226696.666666668
      },
      {
        "stddev": 452.35421224227963,
        "x": 10416.666666666666,
        "y": 31607691.333333332
      }
    ]
  }
}