{
  "inputs": [
    [
      "high-extra-refills",
      0
    ],
    [
      "high-budget",
      120
    ],
    [
      "low-period",
      12500
    ],
    [
      "timer-both",
      true
    ]
  ],
  "series": {
    "irq-bounded/[Interrupt]": [
      {
        "stddev": 115.51767541520793,
        "x": 83333.33333333333,
        "y": 44334.666666666664
      },
      {
        "stddev": 79.0,
        "x": 41666.666666666664,
        "y": 26375
      },
      {
        "stddev": 22.744962812309307,
        "x": 20833.333333333332,
        "y": 14554.666666666666
      },
      {
        "stddev": 4.932882862316247,
        "x": 10416.666666666666,
        "y": 7676.666666666667
      }
    ],
    "sporadic/[Interrupt]": [
      {
        "stddev": 20.840665376454115,
        "x": 83333.33333333333,
        "y": 44999.666666666664
      },
      {
        "stddev": 3.2145502536643185,
        "x": 41666.666666666664,
        "y": 27942.333333333332
      },
      {
        "stddev": 8.18535277187245,
        "x": 20833.333333333332,
        "y": 16118
      },
      {
        "stddev": 11.239810200058244,
        "x": 10416.666666666666,
        "y": 8678.333333333334
      }
    ]
  }
}