{
  "inputs": [
    [
      "high-extra-refills",
      0
    ],
    [
      "high-budget",
      240
    ],
    [
      "low-period",
      25000
    ],
    [
      "timer-both",
      false
    ]
  ],
  "series": {
    "irq-bounded/[Interrupt]": [
      {
        "stddev": 418.7724123355469,
        "x": 83333.33333333333,
        "y": 100034.33333333333
      },
      {
        "stddev": 398.4499132053279,
        "x": 41666.666666666664,
        "y": 61078.333333333336
      },
      {
        "stddev": 17.897858344878397,
        "x": 20833.333333333332,
        "y": 34201.333333333336
      },
      {
        "stddev": 47.982635748084256,
        "x": 10416.666666666666,
        "y": 18155.666666666668
      }
    ],
    "sporadic/[Interrupt]": [
      {
        "stddev": 18.14754345175493,
        "x": 83333.33333333333,
        "y": 108625.66666666667
      },
      {
        "stddev": 2.6457513110645907,
        "x": 41666.666666666664,
        "y": 68290
      },
      {
        "stddev": 7.505553499465135,
        "x": 20833.333333333332,
        "y": 39199.666666666664
      },
      {
        "stddev": 1.5275252316519465,
        "x": 10416.666666666666,
        "y": 21169.333333333332
      }
    ]
  }
}