{
  "inputs": [
    [
      "high-extra-refills",
      4
    ],
    [
      "high-budget",
      60
    ],
    [
      "low-period",
      50000
    ],
    [
      "timer-both",
      false
    ]
  ],
  "series": {
    "correct-charge/[Interrupt]": [
      {
        "stddev": 3857.0268342338504,
        "x": 83333.33333333333,
        "y": 31905430
      },
      {
        "stddev": 5321.830418192598,
        "x": 41666.666666666664,
        "y": 31898169
      },
      {
        "stddev": 4263.657936561046,
        "x": 20833.333333333332,
        "y": 31904417
      },
      {
        "stddev": 1840.2647454465168,
        "x": 10416.666666666666,
        "y": 31951704.333333332
      }
    ],
    "irq-bounded/[Interrupt]": [
      {
        "stddev": 35351.97942124316,
        "x": 83333.33333333333,
        "y": 31963777
      },
      {
        "stddev": 6163.922371347647,
        "x": 41666.666666666664,
        "y": 31913674
      },
      {
        "stddev": 2275.737536126109,
        "x": 20833.333333333332,
        "y": 31916642.333333332
      },
      {
        "stddev": 767.815298970614,
        "x": 10416.666666666666,
        "y": 31954425.333333332
      }
    ],
    "sporadic/[Interrupt]": [
      {
        "stddev": 12269.090553093167,
        "x": 83333.33333333333,
        "y": 30872400
      },
      {
        "stddev": 3245.475979472554,
        "x": 41666.666666666664,
        "y": 30903601.333333332
      },
      {
        "stddev": 9329.811698707179,
        "x": 20833.333333333332,
        "y": 30991931.666666668
      },
      {
        "stddev": 722.2231880335422,
        "x": 10416.666666666666,
        "y": 31394768.666666668
      }
    ]
  }
}