{
  "inputs": [
    [
      "high-extra-refills",
      4
    ],
    [
      "high-budget",
      240
    ],
    [
      "low-period",
      100000
    ],
    [
      "timer-both",
      false
    ]
  ],
  "series": {
    "correct-charge/[Interrupt]": [
      {
        "stddev": 1858.2992224074142,
        "x": 83333.33333333333,
        "y": 31664934
      },
      {
        "stddev": 3989.3062471228423,
        "x": 41666.666666666664,
        "y": 31826223.666666668
      },
      {
        "stddev": 1878.8355436280208,
        "x": 20833.333333333332,
        "y": 31911829
      },
      {
        "stddev": 549.5334384730378,
        "x": 10416.666666666666,
        "y": 31951840
      }
    ],
    "irq-bounded/[Interrupt]": [
      {
        "stddev": 6509.137372442937,
        "x": 83333.33333333333,
        "y": 31671095.333333332
      },
      {
        "stddev": 1345.7549306368278,
        "x": 41666.666666666664,
        "y": 31838394.666666668
      },
      {
        "stddev": 1405.2808734674122,
        "x": 20833.333333333332,
        "y": 31918566.333333332
      },
      {
        "stddev": 1928.8462872919656,
        "x": 10416.666666666666,
        "y": 31952595
      }
    ],
    "sporadic/[Interrupt]": [
      {
        "stddev": 8788.253599739446,
        "x": 83333.33333333333,
        "y": 26701040.333333332
      },
      {
        "stddev": 1387.3003760301276,
        "x": 41666.666666666664,
        "y": 29498917.333333332
      },
      {
        "stddev": 1855.0715170400663,
        "x": 20833.333333333332,
        "y": 30779773.333333332
      },
      {
        "stddev": 1044.2367228427343,
        "x": 10416.666666666666,
        "y": 31393544.333333332
      }
    ]
  }
}